func_colors/__init__.py
func_colors/colors.py
func_colors-0.1.2.dist-info/LICENSE
func_colors-0.1.2.dist-info/WHEEL
func_colors-0.1.2.dist-info/METADATA
func_colors-0.1.2.dist-info/RECORD
