Metadata-Version: 2.1
Name: func-colors
Version: 0.1.2
Summary: Debug colors
Author-email: Jonas Castro <jonasalves15@live.com>
Requires-Dist: pytest ; extra == "test"
Requires-Dist: isort ; extra == "test"
Requires-Dist: flake8 ; extra == "test"
Provides-Extra: test
